LICENSE
MANIFEST.in
copr-cli.spec
requirements.txt
run_tests.sh
setup.py
copr_cli/README.rst
copr_cli/__init__.py
copr_cli/build_config.py
copr_cli/helpers.py
copr_cli/main.py
copr_cli/monitor.py
copr_cli/package_build_order.py
copr_cli/printers.py
copr_cli/util.py
copr_cli.egg-info/PKG-INFO
copr_cli.egg-info/SOURCES.txt
copr_cli.egg-info/dependency_links.txt
copr_cli.egg-info/entry_points.txt
copr_cli.egg-info/not-zip-safe
copr_cli.egg-info/requires.txt
copr_cli.egg-info/top_level.txt
man/copr-cli.1.asciidoc
man/copr-cli.cheat
man/copr.1
tests/cli_tests_lib.py
tests/test_cli.py
tests/test_distgit.py
tests/test_mock_config.py
tests/test_util.py
tests/resources/get_package_expected.json
tests/resources/get_package_response.json
tests/resources/get_package_response_builds.json
tests/resources/get_project_expected.txt
tests/resources/get_project_response.json
tests/resources/list_builds_expected.txt
tests/resources/list_builds_response.json
tests/resources/list_packages_expected.json
tests/resources/list_packages_response.json
tests/resources/list_projects_expected.txt
tests/resources/list_projects_response.json