Metadata-Version: 2.1
Name: copr-cli
Version: 2.2
Summary: CLI tool to run copr
Home-page: https://github.com/fedora-copr/copr
Author: Pierre-Yves Chibon
Author-email: pingou@pingoured.fr
License: GPLv2+
Classifier: License :: OSI Approved :: GNU General Public License v2 or later (GPLv2+)
Classifier: Programming Language :: Python :: 2
Classifier: Programming Language :: Python :: 2.7
Classifier: Topic :: System :: Archiving :: Packaging
Classifier: Development Status :: 3 - Alpha
License-File: LICENSE
Requires-Dist: copr
Requires-Dist: humanize
Requires-Dist: jinja2
Requires-Dist: setuptools
